{
  "meta": {
    "source": "Every Noise at Once (everynoise.com)",
    "description": "Complete Spotify genre taxonomy",
    "fetchedAt": "2025-11-14T02:23:08.186Z",
    "totalGenres": 21,
    "note": "These are all genres used in Spotify's internal classification system"
  },
  "genres": [
    "&nbsp;<br>",
    "&nbsp;<br>",
    "<!--I have been to all of these places in my heart-->",
    "<!--the body is divided by hearsay, but united by salience-->",
    "<!--there is no metal cold enough to separate failure from conscience-->",
    "<!--where nothing is tolerated in darkness, we will malinger brightly-->",
    "</body>",
    "</head>",
    "</html>",
    "</style>",
    "<a href=\"https://www.everynoise.com\"><b>www.everynoise.com</b></a>",
    "<body>",
    "<head>",
    "<html>",
    "<style>",
    "<title>our sadness of 404</title>",
    "and not all of the pages survive<br>",
    "and then go again in search of new songs<br>",
    "body\t{margin: 100px; text-align: center; border: 0px; font: 90%/130% Trebuchet MS, Arial, Helvetica, sans-serif;}",
    "chapters sometimes close abruptly<br>",
    "we pause in memory<br>"
  ]
}